histcite/__init__.py
histcite/__main__.py
histcite/compute_metrics.py
histcite/network_graph.py
histcite/parse_reference.py
histcite/process_file.py
histcite/read_file.py
histcite_python-2.1.0.dist-info/LICENSE
histcite_python-2.1.0.dist-info/METADATA
histcite_python-2.1.0.dist-info/WHEEL
histcite_python-2.1.0.dist-info/entry_points.txt
histcite_python-2.1.0.dist-info/top_level.txt
histcite_python-2.1.0.dist-info/RECORD
