Metadata-Version: 2.1
Name: histcite-python
Version: 2.1.0
Summary: A Python interface for histcite
Author-email: WangK2 <kw221225@gmail.com>
License: MIT
Project-URL: Repository, https://github.com/doublessay/histcite-python
Keywords: histcite,citation network,web of science,scopus,cssci
Classifier: Development Status :: 5 - Production/Stable
Classifier: Intended Audience :: Science/Research
Classifier: License :: OSI Approved :: MIT License
Classifier: Programming Language :: Python :: 3
Classifier: Programming Language :: Python :: 3 :: Only
Classifier: Programming Language :: Python :: 3.9
Classifier: Programming Language :: Python :: 3.10
Classifier: Programming Language :: Python :: 3.11
Classifier: Programming Language :: Python :: 3.12
Classifier: Operating System :: OS Independent
Classifier: Topic :: Scientific/Engineering :: Information Analysis
Classifier: Typing :: Typed
Requires-Python: >=3.9
License-File: LICENSE
Requires-Dist: pandas >=2.0
Requires-Dist: pyarrow
Requires-Dist: openpyxl
Requires-Dist: refparse
Provides-Extra: dev
Requires-Dist: black ; extra == 'dev'
Requires-Dist: coverage ; extra == 'dev'
Requires-Dist: mypy ; extra == 'dev'
Requires-Dist: pre-commit ; extra == 'dev'
Requires-Dist: pytest ; extra == 'dev'
